LICENSE
ptimeit/__init__.py
ptimeit/helpers.py
ptimeit/ptimeit.py
pretty_timeit-0.1.0.dist-info/LICENSE
pretty_timeit-0.1.0.dist-info/WHEEL
pretty_timeit-0.1.0.dist-info/METADATA
pretty_timeit-0.1.0.dist-info/RECORD
