Metadata-Version: 2.1
Name: pretty-timeit
Version: 0.1.0
Summary: timeit, but with the interface it should have had.
Home-page: https://github.com/AbhinavOmprakash/pretty-timeit
License: BSD-3-Clause
Keywords: Timer,timeit
Author: Abhinav Omprakash
Requires-Python: >=3.6.2,<4.0.0
Classifier: License :: OSI Approved :: BSD License
Classifier: Programming Language :: Python :: 3
Classifier: Programming Language :: Python :: 3.7
Classifier: Programming Language :: Python :: 3.8
Classifier: Programming Language :: Python :: 3.9
Project-URL: Repository, https://github.com/AbhinavOmprakash/pretty-timeit
